pyppbox/__init__.py
pyppbox/config/__init__.py
pyppbox/config/configtools.py
pyppbox/config/myconfig.py
pyppbox/config/unifiedstrings.py
pyppbox/config/cfg/cfg.zip
pyppbox/config/cfg/detectors.yaml
pyppbox/config/cfg/main.yaml
pyppbox/config/cfg/reiders.yaml
pyppbox/config/cfg/trackers.yaml
pyppbox/config/strings/strings.yaml
pyppbox/config/strings/strings.zip
pyppbox/data/datasets/.gitignore
pyppbox/data/logs/.gitignore
pyppbox/data/modules/.gitignore
pyppbox/data/res/.gitignore
pyppbox/data/res/idmap.txt
pyppbox/gui/__init__.py
pyppbox/gui/guidemo.py
pyppbox/gui/guihub.py
pyppbox/gui/guitools.py
pyppbox/gui/ui_centroid.py
pyppbox/gui/ui_deepsort.py
pyppbox/gui/ui_facenet.py
pyppbox/gui/ui_gt.py
pyppbox/gui/ui_launcher.py
pyppbox/gui/ui_sort.py
pyppbox/gui/ui_torchreid.py
pyppbox/gui/ui_yolocls.py
pyppbox/gui/ui_yoloult.py
pyppbox/gui/assets/TReID.png
pyppbox/gui/assets/icon.ico
pyppbox/gui/assets/settings.ico
pyppbox/gui/tmp/input.tmp
pyppbox/gui/tmp/ui.tmp
pyppbox/modules/__init__.py
pyppbox/modules/detectors/__init__.py
pyppbox/modules/detectors/yolocls/__init__.py
pyppbox/modules/detectors/yoloult/__init__.py
pyppbox/modules/reiders/__init__.py
pyppbox/modules/reiders/facenet/__init__.py
pyppbox/modules/reiders/facenet/origin/align.cmd
pyppbox/modules/reiders/facenet/origin/align_dataset_mtcnn.py
pyppbox/modules/reiders/facenet/origin/detect_face.py
pyppbox/modules/reiders/facenet/origin/facenet.py
pyppbox/modules/reiders/torchreid/__init__.py
pyppbox/modules/reiders/torchreid/model_dict.py
pyppbox/modules/reiders/torchreid/model_dict.yaml
pyppbox/modules/reiders/torchreid/utils.py
pyppbox/modules/trackers/__init__.py
pyppbox/modules/trackers/centroid/__init__.py
pyppbox/modules/trackers/deepsort/__init__.py
pyppbox/modules/trackers/deepsort/origin/detection.py
pyppbox/modules/trackers/deepsort/origin/detection_yolo.py
pyppbox/modules/trackers/deepsort/origin/generate_detections.py
pyppbox/modules/trackers/deepsort/origin/iou_matching.py
pyppbox-3.13.0.dist-info/licenses/LICENSE
pyppbox-3.13.0.dist-info/METADATA
pyppbox-3.13.0.dist-info/WHEEL
pyppbox-3.13.0.dist-info/top_level.txt
pyppbox-3.13.0.dist-info/RECORD
