Metadata-Version: 2.4
Name: pyppbox
Version: 3.13.0
Summary: Toolbox for people detecting, tracking, and re-identifying.
Home-page: https://github.com/rathaumons/pyppbox
Author: Ratha SIV
Maintainer: rathaROG
License: GPL-3.0-or-later
Keywords: Toolbox,People Detecting,People Tracking,People Re-Identification
Classifier: Development Status :: 4 - Beta
Classifier: Environment :: Console
Classifier: Intended Audience :: Developers
Classifier: Intended Audience :: Education
Classifier: Intended Audience :: Information Technology
Classifier: Intended Audience :: Science/Research
Classifier: Programming Language :: Python
Classifier: Programming Language :: Python :: 3
Classifier: Programming Language :: Python :: 3 :: Only
Classifier: Programming Language :: Python :: 3.9
Classifier: Programming Language :: Python :: 3.10
Classifier: Programming Language :: Python :: 3.11
Classifier: Programming Language :: Python :: 3.12
Classifier: Topic :: Scientific/Engineering
Classifier: Topic :: Scientific/Engineering :: Image Recognition
Classifier: Topic :: Software Development
Classifier: Operating System :: Microsoft :: Windows
Classifier: Operating System :: POSIX
Classifier: Operating System :: Unix
Classifier: Operating System :: MacOS
Requires-Python: >=3.9
License-File: LICENSE
Requires-Dist: Cython>=0.29.37
Requires-Dist: numpy
Requires-Dist: opencv-contrib-python
Requires-Dist: scikit-image>=0.20.0
Requires-Dist: scikit-learn>=1.2.2
Requires-Dist: scipy>=1.10.0
Requires-Dist: imageio
Requires-Dist: matplotlib
Requires-Dist: PyYAML
Requires-Dist: protobuf
Requires-Dist: tensorflow
Requires-Dist: torch
Requires-Dist: torchvision
Requires-Dist: filterpy
Requires-Dist: lapx>=0.6.0
Requires-Dist: PyQt6
Requires-Dist: sfps
Requires-Dist: pyppbox-torchreid
Requires-Dist: vsensebox-ultralytics>=8.3.5
Dynamic: author
Dynamic: classifier
Dynamic: description
Dynamic: description-content-type
Dynamic: home-page
Dynamic: keywords
Dynamic: license
Dynamic: license-file
Dynamic: maintainer
Dynamic: requires-dist
Dynamic: requires-python
Dynamic: summary
